bin
senseme
