Metadata-Version: 2.1
Name: SenseMe
Version: 0.1.5
Summary: HaikuHome SenseMe API for fans and lights
Home-page: https://github.com/TomFaulkner/SenseMe
Author: Tom Faulkner
Author-email: tomfaulkner@gmail.com
License: GPL3
Keywords: HaikuHome SenseMe fan light home automation bigassfans
Platform: UNKNOWN
Classifier: Development Status :: 3 - Alpha
Classifier: Intended Audience :: Developers
Classifier: Programming Language :: Python :: 3.6
Classifier: Programming Language :: Python :: 3.7
Classifier: Topic :: Home Automation
Requires-Python: >=3.6
